luhnchecker/__init__.py
luhnchecker/__main__.py
luhnchecker/luhn.py
luhnchecker-0.0.12.dist-info/LICENSE
luhnchecker-0.0.12.dist-info/METADATA
luhnchecker-0.0.12.dist-info/WHEEL
luhnchecker-0.0.12.dist-info/entry_points.txt
luhnchecker-0.0.12.dist-info/top_level.txt
luhnchecker-0.0.12.dist-info/RECORD
