Metadata-Version: 2.1
Name: luhnchecker
Version: 0.0.12
Summary: An helper tool that verify the validity of credit card numbers.
Author-email: team 111 <khl446@nyu.edu>
License: GNU GENERAL PUBLIC LICENSE
Project-URL: luhntesters, https://github.com/software-students-fall2023/3-python-package-exercise-111/tree/main/tests
Project-URL: Repository, https://github.com/software-students-fall2023/3-python-package-exercise-111
Project-URL: luhnchecker, https://github.com/software-students-fall2023/3-python-package-exercise-111/tree/main/src/luhnchecker
Keywords: python,package,build,tutorial
Classifier: Programming Language :: Python :: 3
Classifier: Intended Audience :: Education
Classifier: License :: OSI Approved :: GNU General Public License v3 (GPLv3)
Classifier: Operating System :: OS Independent
Requires-Python: >=3.7
License-File: LICENSE
Provides-Extra: dev
Requires-Dist: pytest ; extra == 'dev'
